odoo8_addon_dead_mans_switch_client-8.0.1.0.1.99.dev34-py3.8-nspkg.pth
odoo_addons/dead_mans_switch_client/README.rst
odoo_addons/dead_mans_switch_client/__init__.py
odoo_addons/dead_mans_switch_client/__openerp__.py
odoo_addons/dead_mans_switch_client/data/ir_actions.xml
odoo_addons/dead_mans_switch_client/data/ir_cron.xml
odoo_addons/dead_mans_switch_client/demo/dead_mans_switch_client_demo.yml
odoo_addons/dead_mans_switch_client/i18n/am.po
odoo_addons/dead_mans_switch_client/i18n/ar.po
odoo_addons/dead_mans_switch_client/i18n/bg.po
odoo_addons/dead_mans_switch_client/i18n/bs.po
odoo_addons/dead_mans_switch_client/i18n/ca.po
odoo_addons/dead_mans_switch_client/i18n/ca_ES.po
odoo_addons/dead_mans_switch_client/i18n/cs.po
odoo_addons/dead_mans_switch_client/i18n/da.po
odoo_addons/dead_mans_switch_client/i18n/de.po
odoo_addons/dead_mans_switch_client/i18n/dead_mans_switch_client.pot
odoo_addons/dead_mans_switch_client/i18n/el_GR.po
odoo_addons/dead_mans_switch_client/i18n/en_GB.po
odoo_addons/dead_mans_switch_client/i18n/es.po
odoo_addons/dead_mans_switch_client/i18n/es_AR.po
odoo_addons/dead_mans_switch_client/i18n/es_CL.po
odoo_addons/dead_mans_switch_client/i18n/es_CO.po
odoo_addons/dead_mans_switch_client/i18n/es_CR.po
odoo_addons/dead_mans_switch_client/i18n/es_DO.po
odoo_addons/dead_mans_switch_client/i18n/es_EC.po
odoo_addons/dead_mans_switch_client/i18n/es_ES.po
odoo_addons/dead_mans_switch_client/i18n/es_MX.po
odoo_addons/dead_mans_switch_client/i18n/es_PE.po
odoo_addons/dead_mans_switch_client/i18n/es_PY.po
odoo_addons/dead_mans_switch_client/i18n/es_VE.po
odoo_addons/dead_mans_switch_client/i18n/et.po
odoo_addons/dead_mans_switch_client/i18n/eu.po
odoo_addons/dead_mans_switch_client/i18n/fa.po
odoo_addons/dead_mans_switch_client/i18n/fi.po
odoo_addons/dead_mans_switch_client/i18n/fr.po
odoo_addons/dead_mans_switch_client/i18n/fr_CA.po
odoo_addons/dead_mans_switch_client/i18n/fr_CH.po
odoo_addons/dead_mans_switch_client/i18n/gl.po
odoo8_addon_dead_mans_switch_client-8.0.1.0.1.99.dev34.dist-info/METADATA
odoo8_addon_dead_mans_switch_client-8.0.1.0.1.99.dev34.dist-info/WHEEL
odoo8_addon_dead_mans_switch_client-8.0.1.0.1.99.dev34.dist-info/namespace_packages.txt
odoo8_addon_dead_mans_switch_client-8.0.1.0.1.99.dev34.dist-info/top_level.txt
odoo8_addon_dead_mans_switch_client-8.0.1.0.1.99.dev34.dist-info/RECORD
